rtklookup/__init__.py
rtklookup/__main__.py
rtklookup/collection.py
rtklookup/colorama.py
rtklookup/config.py
rtklookup/handler.py
rtklookup/log.py
rtklookup/lookup.py
rtklookup/resultprinter.py
rtklookup/searchresults.py
rtklookup/ui.py
rtklookup/util.py
rtklookup/version.txt
rtklookup/config/default.config
rtklookup/data/rtk_data.tsv
rtk_lookup-1.0.0.dist-info/METADATA
rtk_lookup-1.0.0.dist-info/WHEEL
rtk_lookup-1.0.0.dist-info/entry_points.txt
rtk_lookup-1.0.0.dist-info/top_level.txt
rtk_lookup-1.0.0.dist-info/RECORD
