Metadata-Version: 2.1
Name: rtk-lookup
Version: 1.0.0
Summary: A command line program that helps looking up kanji in James Heisig's book
Home-page: https://github.com/klieret/rtk-lookup
Author: Kilian Lieret
Author-email: kilian.lieret@arcor.de
License: AGPLv3.0+
Platform: UNKNOWN
Classifier: Programming Language :: Python :: 3
Classifier: License :: OSI Approved :: GNU Affero General Public License v3 or later (AGPLv3+)
Classifier: Operating System :: OS Independent
Requires-Python: >=3.5
Requires-Dist: colorama
Requires-Dist: romkan
Requires-Dist: colorlog
